{
  "transactions": [
    {
      "hash": "0x123...",
      "timeStamp": "1678901234",
      "value": "1000000000000000000",
      "gas": "21000",
      "gasPrice": "50000000000"
    },
    {
      "hash": "0x456...",
      "timeStamp": "1678901235",
      "value": "100000000000000000000",
      "gas": "150000",
      "gasPrice": "100000000000"
    },
    {
      "hash": "0x789...",
      "timeStamp": "1678901236",
      "value": "500000000000000000",
      "gas": "21000",
      "gasPrice": "40000000000"
    }
  ]
} 